splent_app/__init__.py
splent_app/migrations/env.py
splent_app/migrations/versions/c93593f90e86_.py
splent_app-0.0.3.dist-info/licenses/LICENSE
splent_app-0.0.3.dist-info/METADATA
splent_app-0.0.3.dist-info/WHEEL
splent_app-0.0.3.dist-info/top_level.txt
splent_app-0.0.3.dist-info/RECORD
